coordax/__init__.py
coordax/coordinate_systems.py
coordax/coordinate_systems_test.py
coordax/coords.py
coordax/doctest_test.py
coordax/experimental.py
coordax/fields.py
coordax/fields_test.py
coordax/jax_datetime_integration_test.py
coordax/named_axes.py
coordax/named_axes_test.py
coordax/ndarrays.py
coordax/testing.py
coordax/utils.py
coordax/xarray_test.py
coordax-0.2.4.dist-info/licenses/LICENSE
coordax-0.2.4.dist-info/METADATA
coordax-0.2.4.dist-info/WHEEL
coordax-0.2.4.dist-info/top_level.txt
coordax-0.2.4.dist-info/RECORD
