Metadata-Version: 2.4
Name: coordax
Version: 0.2.4
Summary: Coordinate axes for scientific computing in JAX
Author-email: Google LLC <noreply@google.com>
License-Expression: Apache-2.0
Project-URL: source, https://github.com/neuralgcm/coordax
Requires-Python: >=3.11
License-File: LICENSE
Requires-Dist: jax
Requires-Dist: numpy
Requires-Dist: treescope
Provides-Extra: complete
Requires-Dist: chex; extra == "complete"
Requires-Dist: jax-datetime; extra == "complete"
Requires-Dist: xarray; extra == "complete"
Provides-Extra: tests
Requires-Dist: absl-py; extra == "tests"
Requires-Dist: pytest; extra == "tests"
Requires-Dist: chex; extra == "tests"
Dynamic: license-file
